[
  {
    "name": "Griso 8V",
    "maker": "Moto Guzzi",
    "model_code": null,
    "displacement": 1151,
    "year": 2010,
    "max_power": 95.1,
    "max_torque": 99.8,
    "seat_height": 800,
    "wet_weight": null,
    "fuel_economy": null,
    "status": "discontinued",
    "image_url": "https://image.bikebros.co.jp/bike_img/0/5725/1_s.jpg",
    "description": "Moto GuzziのBikeBrosカタログ掲載モデル。 2010年発売 1151cc ネイキッド",
    "tags": [
      "Moto Guzzi",
      "ネイキッド",
      "空冷",
      "テレスコピックフォーク",
      "モノショック",
      "L型",
      "二気筒",
      "4バルブ",
      "フューエルインジェクション",
      "乾式クラッチ",
      "セルスタート",
      "MT 6速",
      "アップライトポジション",
      "通勤・街乗り"
    ]
  },
  {
    "name": "Griso 8V Special Edition",
    "maker": "Moto Guzzi",
    "model_code": null,
    "displacement": 1151,
    "year": 2010,
    "max_power": 95.1,
    "max_torque": 99.8,
    "seat_height": 800,
    "wet_weight": null,
    "fuel_economy": null,
    "status": "discontinued",
    "image_url": "https://image.bikebros.co.jp/bike_img/0/5726/1_s.jpg",
    "description": "Moto GuzziのBikeBrosカタログ掲載モデル。 2010年発売 1151cc ネイキッド",
    "tags": [
      "Moto Guzzi",
      "ネイキッド",
      "空冷",
      "テレスコピックフォーク",
      "モノショック",
      "L型",
      "二気筒",
      "4バルブ",
      "フューエルインジェクション",
      "乾式クラッチ",
      "セルスタート",
      "MT 6速",
      "アップライトポジション",
      "通勤・街乗り"
    ]
  },
  {
    "name": "V7 Cafe Classic",
    "maker": "Moto Guzzi",
    "model_code": null,
    "displacement": 744,
    "year": 2010,
    "max_power": 40.1,
    "max_torque": 50.0,
    "seat_height": 805,
    "wet_weight": null,
    "fuel_economy": null,
    "status": "discontinued",
    "image_url": "https://image.bikebros.co.jp/bike_img/0/5762/1_s.jpg",
    "description": "Moto GuzziのBikeBrosカタログ掲載モデル。 2010年発売 744cc ネイキッド",
    "tags": [
      "Moto Guzzi",
      "ネイキッド",
      "空冷",
      "テレスコピックフォーク",
      "モノショック",
      "L型",
      "二気筒",
      "2バルブ",
      "フューエルインジェクション",
      "乾式クラッチ",
      "シャフトドライブ",
      "セルスタート",
      "MT 5速",
      "アップライトポジション",
      "通勤・街乗り"
    ]
  },
  {
    "name": "1000S",
    "maker": "Moto Guzzi",
    "model_code": null,
    "displacement": null,
    "year": 2011,
    "max_power": null,
    "max_torque": null,
    "seat_height": null,
    "wet_weight": null,
    "fuel_economy": null,
    "status": "discontinued",
    "image_url": "https://image.bikebros.co.jp/bike_img/no_photo_s.jpg",
    "description": "Moto GuzziのBikeBrosカタログ掲載モデル。 2011年発売 ツアラー",
    "tags": [
      "Moto Guzzi",
      "ツアラー",
      "アップライトポジション",
      "ツーリング"
    ]
  },
  {
    "name": "1000SP",
    "maker": "Moto Guzzi",
    "model_code": null,
    "displacement": null,
    "year": 2011,
    "max_power": null,
    "max_torque": null,
    "seat_height": null,
    "wet_weight": null,
    "fuel_economy": null,
    "status": "discontinued",
    "image_url": "https://image.bikebros.co.jp/bike_img/no_photo_s.jpg",
    "description": "Moto GuzziのBikeBrosカタログ掲載モデル。 2011年発売 ツアラー",
    "tags": [
      "Moto Guzzi",
      "ツアラー",
      "アップライトポジション",
      "ツーリング"
    ]
  },
  {
    "name": "1100 Sport",
    "maker": "Moto Guzzi",
    "model_code": null,
    "displacement": null,
    "year": 2011,
    "max_power": null,
    "max_torque": null,
    "seat_height": null,
    "wet_weight": null,
    "fuel_economy": null,
    "status": "discontinued",
    "image_url": "https://image.bikebros.co.jp/bike_img/no_photo_s.jpg",
    "description": "Moto GuzziのBikeBrosカタログ掲載モデル。 2011年発売 ツアラー",
    "tags": [
      "Moto Guzzi",
      "ツアラー",
      "アップライトポジション",
      "ツーリング"
    ]
  },
  {
    "name": "1100 Sport Corsa",
    "maker": "Moto Guzzi",
    "model_code": null,
    "displacement": null,
    "year": 2011,
    "max_power": null,
    "max_torque": null,
    "seat_height": null,
    "wet_weight": null,
    "fuel_economy": null,
    "status": "discontinued",
    "image_url": "https://image.bikebros.co.jp/bike_img/no_photo_s.jpg",
    "description": "Moto GuzziのBikeBrosカタログ掲載モデル。 2011年発売 ツアラー",
    "tags": [
      "Moto Guzzi",
      "ツアラー",
      "アップライトポジション",
      "ツーリング"
    ]
  },
  {
    "name": "1100S",
    "maker": "Moto Guzzi",
    "model_code": null,
    "displacement": null,
    "year": 2011,
    "max_power": null,
    "max_torque": null,
    "seat_height": null,
    "wet_weight": null,
    "fuel_economy": null,
    "status": "discontinued",
    "image_url": "https://image.bikebros.co.jp/bike_img/no_photo_s.jpg",
    "description": "Moto GuzziのBikeBrosカタログ掲載モデル。 2011年発売 ツアラー",
    "tags": [
      "Moto Guzzi",
      "ツアラー",
      "アップライトポジション",
      "ツーリング"
    ]
  },
  {
    "name": "1200 Sport",
    "maker": "Moto Guzzi",
    "model_code": null,
    "displacement": null,
    "year": 2011,
    "max_power": null,
    "max_torque": null,
    "seat_height": null,
    "wet_weight": null,
    "fuel_economy": null,
    "status": "discontinued",
    "image_url": "https://image.bikebros.co.jp/bike_img/no_photo_s.jpg",
    "description": "Moto GuzziのBikeBrosカタログ掲載モデル。 2011年発売 ネイキッド",
    "tags": [
      "Moto Guzzi",
      "ネイキッド",
      "アップライトポジション",
      "通勤・街乗り"
    ]
  },
  {
    "name": "AUDACE",
    "maker": "Moto Guzzi",
    "model_code": null,
    "displacement": 1380,
    "year": 2011,
    "max_power": null,
    "max_torque": 121.0,
    "seat_height": 740,
    "wet_weight": 299,
    "fuel_economy": null,
    "status": "discontinued",
    "image_url": "https://image.bikebros.co.jp/bike_img/no_photo_s.jpg",
    "description": "Moto GuzziのBikeBrosカタログ掲載モデル。 2011年発売 1380cc クルーザー",
    "tags": [
      "Moto Guzzi",
      "クルーザー",
      "油冷",
      "テレスコピックフォーク",
      "モノショック",
      "クレードルフレーム",
      "L型",
      "二気筒",
      "4バルブ",
      "フューエルインジェクション",
      "MT 6速",
      "クルーザーポジション",
      "ツーリング"
    ]
  },
  {
    "name": "AUDACE CARBON",
    "maker": "Moto Guzzi",
    "model_code": null,
    "displacement": 1380,
    "year": 2011,
    "max_power": null,
    "max_torque": 121.0,
    "seat_height": 740,
    "wet_weight": 299,
    "fuel_economy": null,
    "status": "discontinued",
    "image_url": "https://image.bikebros.co.jp/bike_img/1/12164/1_s.jpg",
    "description": "Moto GuzziのBikeBrosカタログ掲載モデル。 2011年発売 1380cc クルーザー",
    "tags": [
      "Moto Guzzi",
      "クルーザー",
      "油冷",
      "テレスコピックフォーク",
      "モノショック",
      "クレードルフレーム",
      "L型",
      "二気筒",
      "4バルブ",
      "フューエルインジェクション",
      "MT 6速",
      "クルーザーポジション",
      "ツーリング"
    ]
  },
  {
    "name": "Breva1100",
    "maker": "Moto Guzzi",
    "model_code": null,
    "displacement": null,
    "year": 2011,
    "max_power": null,
    "max_torque": null,
    "seat_height": null,
    "wet_weight": null,
    "fuel_economy": null,
    "status": "discontinued",
    "image_url": "https://image.bikebros.co.jp/bike_img/no_photo_s.jpg",
    "description": "Moto GuzziのBikeBrosカタログ掲載モデル。 2011年発売 ツアラー",
    "tags": [
      "Moto Guzzi",
      "ツアラー",
      "アップライトポジション",
      "ツーリング"
    ]
  },
  {
    "name": "Breva750",
    "maker": "Moto Guzzi",
    "model_code": null,
    "displacement": 744,
    "year": 2011,
    "max_power": null,
    "max_torque": null,
    "seat_height": null,
    "wet_weight": null,
    "fuel_economy": null,
    "status": "discontinued",
    "image_url": "https://image.bikebros.co.jp/bike_img/0/5712/1_s.jpg",
    "description": "Moto GuzziのBikeBrosカタログ掲載モデル。 2011年発売 744cc ツアラー",
    "tags": [
      "Moto Guzzi",
      "ツアラー",
      "空冷",
      "テレスコピックフォーク",
      "モノショック",
      "L型",
      "二気筒",
      "2バルブ",
      "シャフトドライブ",
      "セルスタート",
      "アップライトポジション",
      "ツーリング",
      "タンデム"
    ]
  },
  {
    "name": "California",
    "maker": "Moto Guzzi",
    "model_code": null,
    "displacement": null,
    "year": 2011,
    "max_power": null,
    "max_torque": null,
    "seat_height": null,
    "wet_weight": null,
    "fuel_economy": null,
    "status": "discontinued",
    "image_url": "https://image.bikebros.co.jp/bike_img/0/5713/1_s.jpg",
    "description": "Moto GuzziのBikeBrosカタログ掲載モデル。 2011年発売 ツアラー",
    "tags": [
      "Moto Guzzi",
      "ツアラー",
      "空冷",
      "テレスコピックフォーク",
      "モノショック",
      "クレードルフレーム",
      "L型",
      "二気筒",
      "2バルブ",
      "シャフトドライブ",
      "セルスタート",
      "アップライトポジション",
      "ツーリング",
      "タンデム"
    ]
  },
  {
    "name": "California 1400 Touring SE",
    "maker": "Moto Guzzi",
    "model_code": null,
    "displacement": 1380,
    "year": 2011,
    "max_power": null,
    "max_torque": 121.0,
    "seat_height": 740,
    "wet_weight": 346,
    "fuel_economy": null,
    "status": "discontinued",
    "image_url": "https://image.bikebros.co.jp/bike_img/1/15005/1_s.jpg",
    "description": "Moto GuzziのBikeBrosカタログ掲載モデル。 2011年発売 1380cc ツアラー",
    "tags": [
      "Moto Guzzi",
      "ツアラー",
      "油冷",
      "テレスコピックフォーク",
      "ツインショック",
      "クレードルフレーム",
      "L型",
      "二気筒",
      "4バルブ",
      "フューエルインジェクション",
      "乾式クラッチ",
      "MT 6速",
      "アップライトポジション",
      "トラクションコントロール有",
      "ライディングモード有",
      "フルデジタル",
      "ツーリング"
    ]
  },
  {
    "name": "California Classic",
    "maker": "Moto Guzzi",
    "model_code": null,
    "displacement": 1063,
    "year": 2011,
    "max_power": null,
    "max_torque": 88.0,
    "seat_height": null,
    "wet_weight": null,
    "fuel_economy": null,
    "status": "discontinued",
    "image_url": "https://image.bikebros.co.jp/bike_img/no_photo_s.jpg",
    "description": "Moto GuzziのBikeBrosカタログ掲載モデル。 2011年発売 1063cc ツアラー",
    "tags": [
      "Moto Guzzi",
      "ツアラー",
      "空冷",
      "テレスコピックフォーク",
      "ツインショック",
      "L型",
      "二気筒",
      "2バルブ",
      "乾式クラッチ",
      "シャフトドライブ",
      "セルスタート",
      "MT 5速",
      "アップライトポジション",
      "アナログ",
      "ツーリング",
      "タンデム"
    ]
  },
  {
    "name": "California EV",
    "maker": "Moto Guzzi",
    "model_code": null,
    "displacement": null,
    "year": 2011,
    "max_power": null,
    "max_torque": null,
    "seat_height": null,
    "wet_weight": null,
    "fuel_economy": null,
    "status": "discontinued",
    "image_url": "https://image.bikebros.co.jp/bike_img/no_photo_s.jpg",
    "description": "Moto GuzziのBikeBrosカタログ掲載モデル。 2011年発売 ツアラー",
    "tags": [
      "Moto Guzzi",
      "ツアラー",
      "アップライトポジション",
      "ツーリング"
    ]
  },
  {
    "name": "California Jackal",
    "maker": "Moto Guzzi",
    "model_code": null,
    "displacement": null,
    "year": 2011,
    "max_power": null,
    "max_torque": null,
    "seat_height": null,
    "wet_weight": null,
    "fuel_economy": null,
    "status": "discontinued",
    "image_url": "https://image.bikebros.co.jp/bike_img/no_photo_s.jpg",
    "description": "Moto GuzziのBikeBrosカタログ掲載モデル。 2011年発売 ツアラー",
    "tags": [
      "Moto Guzzi",
      "ツアラー",
      "アップライトポジション",
      "ツーリング"
    ]
  },
  {
    "name": "California SS Aluminum",
    "maker": "Moto Guzzi",
    "model_code": null,
    "displacement": null,
    "year": 2011,
    "max_power": null,
    "max_torque": null,
    "seat_height": null,
    "wet_weight": null,
    "fuel_economy": null,
    "status": "discontinued",
    "image_url": "https://image.bikebros.co.jp/bike_img/no_photo_s.jpg",
    "description": "Moto GuzziのBikeBrosカタログ掲載モデル。 2011年発売 ツアラー",
    "tags": [
      "Moto Guzzi",
      "ツアラー",
      "アップライトポジション",
      "ツーリング"
    ]
  },
  {
    "name": "California Stone",
    "maker": "Moto Guzzi",
    "model_code": null,
    "displacement": null,
    "year": 2011,
    "max_power": null,
    "max_torque": null,
    "seat_height": null,
    "wet_weight": null,
    "fuel_economy": null,
    "status": "discontinued",
    "image_url": "https://image.bikebros.co.jp/bike_img/no_photo_s.jpg",
    "description": "Moto GuzziのBikeBrosカタログ掲載モデル。 2011年発売 ツアラー",
    "tags": [
      "Moto Guzzi",
      "ツアラー",
      "アップライトポジション",
      "ツーリング"
    ]
  },
  {
    "name": "California Vintage",
    "maker": "Moto Guzzi",
    "model_code": null,
    "displacement": 1063,
    "year": 2011,
    "max_power": null,
    "max_torque": 88.0,
    "seat_height": null,
    "wet_weight": null,
    "fuel_economy": null,
    "status": "discontinued",
    "image_url": "https://image.bikebros.co.jp/bike_img/no_photo_s.jpg",
    "description": "Moto GuzziのBikeBrosカタログ掲載モデル。 2011年発売 1063cc ツアラー",
    "tags": [
      "Moto Guzzi",
      "ツアラー",
      "空冷",
      "テレスコピックフォーク",
      "ツインショック",
      "L型",
      "二気筒",
      "2バルブ",
      "フューエルインジェクション",
      "乾式クラッチ",
      "シャフトドライブ",
      "セルスタート",
      "MT 5速",
      "アップライトポジション",
      "アナログ",
      "ツーリング",
      "タンデム"
    ]
  },
  {
    "name": "DAYTONA 1000",
    "maker": "Moto Guzzi",
    "model_code": null,
    "displacement": null,
    "year": 2011,
    "max_power": null,
    "max_torque": null,
    "seat_height": null,
    "wet_weight": null,
    "fuel_economy": null,
    "status": "discontinued",
    "image_url": "https://image.bikebros.co.jp/bike_img/0/5720/1_s.jpg",
    "description": "Moto GuzziのBikeBrosカタログ掲載モデル。 2011年発売 ツアラー",
    "tags": [
      "Moto Guzzi",
      "ツアラー",
      "空冷",
      "テレスコピックフォーク",
      "モノショック",
      "L型",
      "二気筒",
      "シャフトドライブ",
      "セルスタート",
      "アップライトポジション",
      "ツーリング",
      "タンデム"
    ]
  },
  {
    "name": "DAYTONA 1000RS",
    "maker": "Moto Guzzi",
    "model_code": null,
    "displacement": null,
    "year": 2011,
    "max_power": null,
    "max_torque": null,
    "seat_height": null,
    "wet_weight": null,
    "fuel_economy": null,
    "status": "discontinued",
    "image_url": "https://image.bikebros.co.jp/bike_img/no_photo_s.jpg",
    "description": "Moto GuzziのBikeBrosカタログ掲載モデル。 2011年発売 ツアラー",
    "tags": [
      "Moto Guzzi",
      "ツアラー",
      "アップライトポジション",
      "ツーリング"
    ]
  },
  {
    "name": "Eldorado",
    "maker": "Moto Guzzi",
    "model_code": null,
    "displacement": 1380,
    "year": 2011,
    "max_power": null,
    "max_torque": 120.0,
    "seat_height": 740,
    "wet_weight": 314,
    "fuel_economy": null,
    "status": "discontinued",
    "image_url": "https://image.bikebros.co.jp/bike_img/1/12162/1_s.jpg",
    "description": "Moto GuzziのBikeBrosカタログ掲載モデル。 2011年発売 1380cc ツアラー",
    "tags": [
      "Moto Guzzi",
      "ツアラー",
      "油冷",
      "テレスコピックフォーク",
      "モノショック",
      "クレードルフレーム",
      "L型",
      "二気筒",
      "4バルブ",
      "フューエルインジェクション",
      "MT 6速",
      "アップライトポジション",
      "ツーリング"
    ]
  },
  {
    "name": "Griso 1100",
    "maker": "Moto Guzzi",
    "model_code": null,
    "displacement": 1064,
    "year": 2011,
    "max_power": null,
    "max_torque": null,
    "seat_height": 790,
    "wet_weight": null,
    "fuel_economy": null,
    "status": "discontinued",
    "image_url": "https://image.bikebros.co.jp/bike_img/0/5722/1_s.jpg",
    "description": "Moto GuzziのBikeBrosカタログ掲載モデル。 2011年発売 1064cc ネイキッド",
    "tags": [
      "Moto Guzzi",
      "ネイキッド",
      "空冷",
      "倒立フォーク",
      "モノショック",
      "クレードルフレーム",
      "L型",
      "二気筒",
      "2バルブ",
      "乾式クラッチ",
      "シャフトドライブ",
      "セルスタート",
      "MT 6速",
      "アップライトポジション",
      "フルデジタル",
      "通勤・街乗り",
      "タンデム"
    ]
  },
  {
    "name": "Griso 850",
    "maker": "Moto Guzzi",
    "model_code": null,
    "displacement": 877,
    "year": 2011,
    "max_power": 75.0,
    "max_torque": 70.0,
    "seat_height": 800,
    "wet_weight": null,
    "fuel_economy": null,
    "status": "discontinued",
    "image_url": "https://image.bikebros.co.jp/bike_img/no_photo_s.jpg",
    "description": "Moto GuzziのBikeBrosカタログ掲載モデル。 2011年発売 877cc ネイキッド",
    "tags": [
      "Moto Guzzi",
      "ネイキッド",
      "空冷",
      "倒立フォーク",
      "モノショック",
      "クレードルフレーム",
      "L型",
      "二気筒",
      "2バルブ",
      "乾式クラッチ",
      "シャフトドライブ",
      "セルスタート",
      "MT 6速",
      "アップライトポジション",
      "フルデジタル",
      "通勤・街乗り",
      "タンデム"
    ]
  },
  {
    "name": "Le Mans 1000",
    "maker": "Moto Guzzi",
    "model_code": null,
    "displacement": null,
    "year": 2011,
    "max_power": null,
    "max_torque": null,
    "seat_height": null,
    "wet_weight": null,
    "fuel_economy": null,
    "status": "discontinued",
    "image_url": "https://image.bikebros.co.jp/bike_img/no_photo_s.jpg",
    "description": "Moto GuzziのBikeBrosカタログ掲載モデル。 2011年発売 ツアラー",
    "tags": [
      "Moto Guzzi",
      "ツアラー",
      "アップライトポジション",
      "ツーリング"
    ]
  },
  {
    "name": "Lodola",
    "maker": "Moto Guzzi",
    "model_code": null,
    "displacement": null,
    "year": 2011,
    "max_power": null,
    "max_torque": null,
    "seat_height": null,
    "wet_weight": null,
    "fuel_economy": null,
    "status": "discontinued",
    "image_url": "https://image.bikebros.co.jp/bike_img/no_photo_s.jpg",
    "description": "Moto GuzziのBikeBrosカタログ掲載モデル。 2011年発売 ネイキッド",
    "tags": [
      "Moto Guzzi",
      "ネイキッド",
      "アップライトポジション",
      "通勤・街乗り"
    ]
  },
  {
    "name": "MGX-21",
    "maker": "Moto Guzzi",
    "model_code": null,
    "displacement": 1380,
    "year": 2011,
    "max_power": null,
    "max_torque": 121.0,
    "seat_height": 740,
    "wet_weight": null,
    "fuel_economy": null,
    "status": "discontinued",
    "image_url": "https://image.bikebros.co.jp/bike_img/1/12161/1_s.jpg",
    "description": "Moto GuzziのBikeBrosカタログ掲載モデル。 2011年発売 1380cc ツアラー",
    "tags": [
      "Moto Guzzi",
      "ツアラー",
      "油冷",
      "テレスコピックフォーク",
      "モノショック",
      "クレードルフレーム",
      "L型",
      "二気筒",
      "4バルブ",
      "フューエルインジェクション",
      "シャフトドライブ",
      "セルスタート",
      "MT 6速",
      "アップライトポジション",
      "ツーリング"
    ]
  },
  {
    "name": "NTX750",
    "maker": "Moto Guzzi",
    "model_code": null,
    "displacement": 744,
    "year": 2011,
    "max_power": null,
    "max_torque": null,
    "seat_height": null,
    "wet_weight": null,
    "fuel_economy": null,
    "status": "discontinued",
    "image_url": "https://image.bikebros.co.jp/bike_img/no_photo_s.jpg",
    "description": "Moto GuzziのBikeBrosカタログ掲載モデル。 2011年発売 744cc オフロード",
    "tags": [
      "Moto Guzzi",
      "オフロード",
      "空冷",
      "L型",
      "二気筒",
      "2バルブ",
      "アップライトポジション",
      "林道・オフロード"
    ]
  },
  {
    "name": "Nevada 750",
    "maker": "Moto Guzzi",
    "model_code": null,
    "displacement": 744,
    "year": 2011,
    "max_power": null,
    "max_torque": null,
    "seat_height": null,
    "wet_weight": null,
    "fuel_economy": null,
    "status": "discontinued",
    "image_url": "https://image.bikebros.co.jp/bike_img/no_photo_s.jpg",
    "description": "Moto GuzziのBikeBrosカタログ掲載モデル。 2011年発売 744cc ツアラー",
    "tags": [
      "Moto Guzzi",
      "ツアラー",
      "空冷",
      "L型",
      "二気筒",
      "2バルブ",
      "アップライトポジション",
      "ツーリング"
    ]
  },
  {
    "name": "Nevada Classic 750",
    "maker": "Moto Guzzi",
    "model_code": null,
    "displacement": 744,
    "year": 2011,
    "max_power": null,
    "max_torque": null,
    "seat_height": null,
    "wet_weight": null,
    "fuel_economy": null,
    "status": "discontinued",
    "image_url": "https://image.bikebros.co.jp/bike_img/no_photo_s.jpg",
    "description": "Moto GuzziのBikeBrosカタログ掲載モデル。 2011年発売 744cc ツアラー",
    "tags": [
      "Moto Guzzi",
      "ツアラー",
      "空冷",
      "L型",
      "二気筒",
      "2バルブ",
      "アップライトポジション",
      "ツーリング"
    ]
  },
  {
    "name": "Nevada Classic 750 IE",
    "maker": "Moto Guzzi",
    "model_code": null,
    "displacement": 744,
    "year": 2011,
    "max_power": null,
    "max_torque": null,
    "seat_height": null,
    "wet_weight": null,
    "fuel_economy": null,
    "status": "discontinued",
    "image_url": "https://image.bikebros.co.jp/bike_img/no_photo_s.jpg",
    "description": "Moto GuzziのBikeBrosカタログ掲載モデル。 2011年発売 744cc ツアラー",
    "tags": [
      "Moto Guzzi",
      "ツアラー",
      "空冷",
      "L型",
      "二気筒",
      "2バルブ",
      "アップライトポジション",
      "ツーリング"
    ]
  },
  {
    "name": "Norge 1200 GT",
    "maker": "Moto Guzzi",
    "model_code": null,
    "displacement": null,
    "year": 2011,
    "max_power": null,
    "max_torque": null,
    "seat_height": null,
    "wet_weight": null,
    "fuel_economy": null,
    "status": "discontinued",
    "image_url": "https://image.bikebros.co.jp/bike_img/no_photo_s.jpg",
    "description": "Moto GuzziのBikeBrosカタログ掲載モデル。 2011年発売 ツアラー",
    "tags": [
      "Moto Guzzi",
      "ツアラー",
      "アップライトポジション",
      "ツーリング"
    ]
  },
  {
    "name": "Quota 1100",
    "maker": "Moto Guzzi",
    "model_code": null,
    "displacement": null,
    "year": 2011,
    "max_power": null,
    "max_torque": null,
    "seat_height": null,
    "wet_weight": null,
    "fuel_economy": null,
    "status": "discontinued",
    "image_url": "https://image.bikebros.co.jp/bike_img/no_photo_s.jpg",
    "description": "Moto GuzziのBikeBrosカタログ掲載モデル。 2011年発売 オフロード",
    "tags": [
      "Moto Guzzi",
      "オフロード",
      "アップライトポジション",
      "林道・オフロード"
    ]
  },
  {
    "name": "Quota 1100RS",
    "maker": "Moto Guzzi",
    "model_code": null,
    "displacement": null,
    "year": 2011,
    "max_power": null,
    "max_torque": null,
    "seat_height": null,
    "wet_weight": null,
    "fuel_economy": null,
    "status": "discontinued",
    "image_url": "https://image.bikebros.co.jp/bike_img/no_photo_s.jpg",
    "description": "Moto GuzziのBikeBrosカタログ掲載モデル。 2011年発売 ツアラー",
    "tags": [
      "Moto Guzzi",
      "ツアラー",
      "アップライトポジション",
      "ツーリング"
    ]
  },
  {
    "name": "STELVIO",
    "maker": "Moto Guzzi",
    "model_code": null,
    "displacement": 1042,
    "year": 2011,
    "max_power": null,
    "max_torque": 105.0,
    "seat_height": 830,
    "wet_weight": 246,
    "fuel_economy": null,
    "status": "discontinued",
    "image_url": "https://image.bikebros.co.jp/bike_img/1/17592/1_s.jpg",
    "description": "Moto GuzziのBikeBrosカタログ掲載モデル。 2011年発売 1042cc ツアラー",
    "tags": [
      "Moto Guzzi",
      "ツアラー",
      "水冷",
      "倒立フォーク",
      "モノショック",
      "L型",
      "二気筒",
      "4バルブ",
      "フューエルインジェクション",
      "湿式クラッチ",
      "シャフトドライブ",
      "ABS",
      "セルスタート",
      "MT 6速",
      "アップライトポジション",
      "トラクションコントロール有",
      "ライディングモード有",
      "フルデジタル",
      "ツーリング",
      "タンデム"
    ]
  },
  {
    "name": "STELVIO1200 4V",
    "maker": "Moto Guzzi",
    "model_code": null,
    "displacement": 1151,
    "year": 2011,
    "max_power": null,
    "max_torque": 108.0,
    "seat_height": 840,
    "wet_weight": null,
    "fuel_economy": null,
    "status": "discontinued",
    "image_url": "https://image.bikebros.co.jp/bike_img/0/5736/1_s.jpg",
    "description": "Moto GuzziのBikeBrosカタログ掲載モデル。 2011年発売 1151cc ツアラー",
    "tags": [
      "Moto Guzzi",
      "ツアラー",
      "空冷",
      "倒立フォーク",
      "モノショック",
      "L型",
      "二気筒",
      "4バルブ",
      "フューエルインジェクション",
      "乾式クラッチ",
      "シャフトドライブ",
      "セルスタート",
      "MT 6速",
      "アップライトポジション",
      "ツーリング",
      "タンデム"
    ]
  },
  {
    "name": "V10 CHENTAURO",
    "maker": "Moto Guzzi",
    "model_code": null,
    "displacement": null,
    "year": 2011,
    "max_power": null,
    "max_torque": null,
    "seat_height": null,
    "wet_weight": null,
    "fuel_economy": null,
    "status": "discontinued",
    "image_url": "https://image.bikebros.co.jp/bike_img/no_photo_s.jpg",
    "description": "Moto GuzziのBikeBrosカタログ掲載モデル。 2011年発売 ネイキッド",
    "tags": [
      "Moto Guzzi",
      "ネイキッド",
      "アップライトポジション",
      "通勤・街乗り"
    ]
  },
  {
    "name": "V10 CHENTAURO SP",
    "maker": "Moto Guzzi",
    "model_code": null,
    "displacement": null,
    "year": 2011,
    "max_power": null,
    "max_torque": null,
    "seat_height": null,
    "wet_weight": null,
    "fuel_economy": null,
    "status": "discontinued",
    "image_url": "https://image.bikebros.co.jp/bike_img/no_photo_s.jpg",
    "description": "Moto GuzziのBikeBrosカタログ掲載モデル。 2011年発売 ネイキッド",
    "tags": [
      "Moto Guzzi",
      "ネイキッド",
      "アップライトポジション",
      "通勤・街乗り"
    ]
  },
  {
    "name": "V100 Mandello Wind Tunnel",
    "maker": "Moto Guzzi",
    "model_code": null,
    "displacement": 1042,
    "year": 2011,
    "max_power": null,
    "max_torque": 105.0,
    "seat_height": 815,
    "wet_weight": 233,
    "fuel_economy": null,
    "status": "discontinued",
    "image_url": "https://image.bikebros.co.jp/bike_img/1/17076/1_s.jpg",
    "description": "Moto GuzziのBikeBrosカタログ掲載モデル。 2011年発売 1042cc ツアラー",
    "tags": [
      "Moto Guzzi",
      "ツアラー",
      "水冷",
      "倒立フォーク",
      "モノショック",
      "L型",
      "二気筒",
      "4バルブ",
      "フューエルインジェクション",
      "湿式クラッチ",
      "シャフトドライブ",
      "セルスタート",
      "MT 6速",
      "アップライトポジション",
      "トラクションコントロール有",
      "ライディングモード有",
      "フルデジタル",
      "ツーリング",
      "タンデム"
    ]
  },
  {
    "name": "V1000",
    "maker": "Moto Guzzi",
    "model_code": null,
    "displacement": null,
    "year": 2011,
    "max_power": null,
    "max_torque": null,
    "seat_height": null,
    "wet_weight": null,
    "fuel_economy": null,
    "status": "discontinued",
    "image_url": "https://image.bikebros.co.jp/bike_img/no_photo_s.jpg",
    "description": "Moto GuzziのBikeBrosカタログ掲載モデル。 2011年発売 ツアラー",
    "tags": [
      "Moto Guzzi",
      "ツアラー",
      "アップライトポジション",
      "ツーリング"
    ]
  },
  {
    "name": "V11 Ballabio",
    "maker": "Moto Guzzi",
    "model_code": null,
    "displacement": null,
    "year": 2011,
    "max_power": null,
    "max_torque": null,
    "seat_height": null,
    "wet_weight": null,
    "fuel_economy": null,
    "status": "discontinued",
    "image_url": "https://image.bikebros.co.jp/bike_img/no_photo_s.jpg",
    "description": "Moto GuzziのBikeBrosカタログ掲載モデル。 2011年発売 ツアラー",
    "tags": [
      "Moto Guzzi",
      "ツアラー",
      "アップライトポジション",
      "ツーリング"
    ]
  },
  {
    "name": "V11 CAFE SPORT",
    "maker": "Moto Guzzi",
    "model_code": null,
    "displacement": 1064,
    "year": 2011,
    "max_power": null,
    "max_torque": 94.0,
    "seat_height": 800,
    "wet_weight": null,
    "fuel_economy": null,
    "status": "discontinued",
    "image_url": "https://image.bikebros.co.jp/bike_img/no_photo_s.jpg",
    "description": "Moto GuzziのBikeBrosカタログ掲載モデル。 2011年発売 1064cc ツアラー",
    "tags": [
      "Moto Guzzi",
      "ツアラー",
      "空冷",
      "倒立フォーク",
      "モノショック",
      "L型",
      "二気筒",
      "4バルブ",
      "フューエルインジェクション",
      "シャフトドライブ",
      "セルスタート",
      "MT 5速",
      "アップライトポジション",
      "ツーリング"
    ]
  },
  {
    "name": "V11 COPPA Italia",
    "maker": "Moto Guzzi",
    "model_code": null,
    "displacement": null,
    "year": 2011,
    "max_power": null,
    "max_torque": null,
    "seat_height": null,
    "wet_weight": null,
    "fuel_economy": null,
    "status": "discontinued",
    "image_url": "https://image.bikebros.co.jp/bike_img/no_photo_s.jpg",
    "description": "Moto GuzziのBikeBrosカタログ掲載モデル。 2011年発売 ツアラー",
    "tags": [
      "Moto Guzzi",
      "ツアラー",
      "アップライトポジション",
      "ツーリング"
    ]
  },
  {
    "name": "V11 Le Mans",
    "maker": "Moto Guzzi",
    "model_code": null,
    "displacement": null,
    "year": 2011,
    "max_power": null,
    "max_torque": null,
    "seat_height": null,
    "wet_weight": null,
    "fuel_economy": null,
    "status": "discontinued",
    "image_url": "https://image.bikebros.co.jp/bike_img/no_photo_s.jpg",
    "description": "Moto GuzziのBikeBrosカタログ掲載モデル。 2011年発売 ツアラー",
    "tags": [
      "Moto Guzzi",
      "ツアラー",
      "アップライトポジション",
      "ツーリング"
    ]
  },
  {
    "name": "V11 Le Mans nero corsa",
    "maker": "Moto Guzzi",
    "model_code": null,
    "displacement": null,
    "year": 2011,
    "max_power": null,
    "max_torque": null,
    "seat_height": null,
    "wet_weight": null,
    "fuel_economy": null,
    "status": "discontinued",
    "image_url": "https://image.bikebros.co.jp/bike_img/no_photo_s.jpg",
    "description": "Moto GuzziのBikeBrosカタログ掲載モデル。 2011年発売 ツアラー",
    "tags": [
      "Moto Guzzi",
      "ツアラー",
      "アップライトポジション",
      "ツーリング"
    ]
  },
  {
    "name": "V11 Le Mans rosso corsa",
    "maker": "Moto Guzzi",
    "model_code": null,
    "displacement": null,
    "year": 2011,
    "max_power": null,
    "max_torque": null,
    "seat_height": null,
    "wet_weight": null,
    "fuel_economy": null,
    "status": "discontinued",
    "image_url": "https://image.bikebros.co.jp/bike_img/no_photo_s.jpg",
    "description": "Moto GuzziのBikeBrosカタログ掲載モデル。 2011年発売 ツアラー",
    "tags": [
      "Moto Guzzi",
      "ツアラー",
      "アップライトポジション",
      "ツーリング"
    ]
  },
  {
    "name": "V11 NAKED",
    "maker": "Moto Guzzi",
    "model_code": null,
    "displacement": null,
    "year": 2011,
    "max_power": null,
    "max_torque": null,
    "seat_height": null,
    "wet_weight": null,
    "fuel_economy": null,
    "status": "discontinued",
    "image_url": "https://image.bikebros.co.jp/bike_img/no_photo_s.jpg",
    "description": "Moto GuzziのBikeBrosカタログ掲載モデル。 2011年発売 ツアラー",
    "tags": [
      "Moto Guzzi",
      "ツアラー",
      "アップライトポジション",
      "ツーリング"
    ]
  },
  {
    "name": "V11 Rosso mandello",
    "maker": "Moto Guzzi",
    "model_code": null,
    "displacement": null,
    "year": 2011,
    "max_power": null,
    "max_torque": null,
    "seat_height": null,
    "wet_weight": null,
    "fuel_economy": null,
    "status": "discontinued",
    "image_url": "https://image.bikebros.co.jp/bike_img/0/5747/1_s.jpg",
    "description": "Moto GuzziのBikeBrosカタログ掲載モデル。 2011年発売 ツアラー",
    "tags": [
      "Moto Guzzi",
      "ツアラー",
      "空冷",
      "倒立フォーク",
      "モノショック",
      "L型",
      "二気筒",
      "シャフトドライブ",
      "セルスタート",
      "アップライトポジション",
      "ツーリング",
      "タンデム"
    ]
  },
  {
    "name": "V11 SPORT",
    "maker": "Moto Guzzi",
    "model_code": null,
    "displacement": null,
    "year": 2011,
    "max_power": null,
    "max_torque": null,
    "seat_height": null,
    "wet_weight": null,
    "fuel_economy": null,
    "status": "discontinued",
    "image_url": "https://image.bikebros.co.jp/bike_img/no_photo_s.jpg",
    "description": "Moto GuzziのBikeBrosカタログ掲載モデル。 2011年発売 ツアラー",
    "tags": [
      "Moto Guzzi",
      "ツアラー",
      "アップライトポジション",
      "ツーリング"
    ]
  },
  {
    "name": "V11 Scura",
    "maker": "Moto Guzzi",
    "model_code": null,
    "displacement": null,
    "year": 2011,
    "max_power": null,
    "max_torque": null,
    "seat_height": null,
    "wet_weight": null,
    "fuel_economy": null,
    "status": "discontinued",
    "image_url": "https://image.bikebros.co.jp/bike_img/no_photo_s.jpg",
    "description": "Moto GuzziのBikeBrosカタログ掲載モデル。 2011年発売 ツアラー",
    "tags": [
      "Moto Guzzi",
      "ツアラー",
      "アップライトポジション",
      "ツーリング"
    ]
  },
  {
    "name": "V35",
    "maker": "Moto Guzzi",
    "model_code": null,
    "displacement": null,
    "year": 2011,
    "max_power": null,
    "max_torque": null,
    "seat_height": null,
    "wet_weight": null,
    "fuel_economy": null,
    "status": "discontinued",
    "image_url": "https://image.bikebros.co.jp/bike_img/0/5750/1_s.jpg",
    "description": "Moto GuzziのBikeBrosカタログ掲載モデル。 2011年発売 ツアラー",
    "tags": [
      "Moto Guzzi",
      "ツアラー",
      "空冷",
      "テレスコピックフォーク",
      "ツインショック",
      "クレードルフレーム",
      "L型",
      "二気筒",
      "2バルブ",
      "乾式クラッチ",
      "シャフトドライブ",
      "セルスタート",
      "アップライトポジション",
      "ツーリング",
      "タンデム"
    ]
  },
  {
    "name": "V35 Imola",
    "maker": "Moto Guzzi",
    "model_code": null,
    "displacement": null,
    "year": 2011,
    "max_power": null,
    "max_torque": null,
    "seat_height": null,
    "wet_weight": null,
    "fuel_economy": null,
    "status": "discontinued",
    "image_url": "https://image.bikebros.co.jp/bike_img/no_photo_s.jpg",
    "description": "Moto GuzziのBikeBrosカタログ掲載モデル。 2011年発売 ツアラー",
    "tags": [
      "Moto Guzzi",
      "ツアラー",
      "アップライトポジション",
      "ツーリング"
    ]
  },
  {
    "name": "V40 Capri",
    "maker": "Moto Guzzi",
    "model_code": null,
    "displacement": null,
    "year": 2011,
    "max_power": null,
    "max_torque": null,
    "seat_height": null,
    "wet_weight": null,
    "fuel_economy": null,
    "status": "discontinued",
    "image_url": "https://image.bikebros.co.jp/bike_img/no_photo_s.jpg",
    "description": "Moto GuzziのBikeBrosカタログ掲載モデル。 2011年発売 ツアラー",
    "tags": [
      "Moto Guzzi",
      "ツアラー",
      "アップライトポジション",
      "ツーリング"
    ]
  },
  {
    "name": "V40 Targa",
    "maker": "Moto Guzzi",
    "model_code": null,
    "displacement": null,
    "year": 2011,
    "max_power": null,
    "max_torque": null,
    "seat_height": null,
    "wet_weight": null,
    "fuel_economy": null,
    "status": "discontinued",
    "image_url": "https://image.bikebros.co.jp/bike_img/no_photo_s.jpg",
    "description": "Moto GuzziのBikeBrosカタログ掲載モデル。 2011年発売 ツアラー",
    "tags": [
      "Moto Guzzi",
      "ツアラー",
      "アップライトポジション",
      "ツーリング"
    ]
  },
  {
    "name": "V50",
    "maker": "Moto Guzzi",
    "model_code": null,
    "displacement": null,
    "year": 2011,
    "max_power": null,
    "max_torque": null,
    "seat_height": null,
    "wet_weight": null,
    "fuel_economy": null,
    "status": "discontinued",
    "image_url": "https://image.bikebros.co.jp/bike_img/1/13954/1_s.jpg",
    "description": "Moto GuzziのBikeBrosカタログ掲載モデル。 2011年発売 ツアラー",
    "tags": [
      "Moto Guzzi",
      "ツアラー",
      "空冷",
      "テレスコピックフォーク",
      "ツインショック",
      "クレードルフレーム",
      "L型",
      "二気筒",
      "2バルブ",
      "乾式クラッチ",
      "シャフトドライブ",
      "セルスタート",
      "アップライトポジション",
      "ツーリング",
      "タンデム"
    ]
  },
  {
    "name": "V65 Lario",
    "maker": "Moto Guzzi",
    "model_code": null,
    "displacement": null,
    "year": 2011,
    "max_power": null,
    "max_torque": null,
    "seat_height": null,
    "wet_weight": null,
    "fuel_economy": null,
    "status": "discontinued",
    "image_url": "https://image.bikebros.co.jp/bike_img/no_photo_s.jpg",
    "description": "Moto GuzziのBikeBrosカタログ掲載モデル。 2011年発売 ツアラー",
    "tags": [
      "Moto Guzzi",
      "ツアラー",
      "アップライトポジション",
      "ツーリング"
    ]
  },
  {
    "name": "V7 SPORT",
    "maker": "Moto Guzzi",
    "model_code": null,
    "displacement": 853,
    "year": 2011,
    "max_power": null,
    "max_torque": 79.0,
    "seat_height": 780,
    "wet_weight": 220,
    "fuel_economy": null,
    "status": "discontinued",
    "image_url": "https://image.bikebros.co.jp/bike_img/1/17594/1_s.jpg",
    "description": "Moto GuzziのBikeBrosカタログ掲載モデル。 2011年発売 853cc ネイキッド",
    "tags": [
      "Moto Guzzi",
      "ネイキッド",
      "空冷",
      "倒立フォーク",
      "ツインショック",
      "クレードルフレーム",
      "L型",
      "二気筒",
      "2バルブ",
      "フューエルインジェクション",
      "乾式クラッチ",
      "シャフトドライブ",
      "ABS",
      "セルスタート",
      "MT 6速",
      "アップライトポジション",
      "トラクションコントロール有",
      "ライディングモード有",
      "フルデジタル",
      "通勤・街乗り",
      "タンデム"
    ]
  },
  {
    "name": "V7 Stone",
    "maker": "Moto Guzzi",
    "model_code": null,
    "displacement": 853,
    "year": 2011,
    "max_power": null,
    "max_torque": 79.0,
    "seat_height": 780,
    "wet_weight": 218,
    "fuel_economy": null,
    "status": "discontinued",
    "image_url": "https://image.bikebros.co.jp/bike_img/1/17593/1_s.jpg",
    "description": "Moto GuzziのBikeBrosカタログ掲載モデル。 2011年発売 853cc ネイキッド",
    "tags": [
      "Moto Guzzi",
      "ネイキッド",
      "空冷",
      "テレスコピックフォーク",
      "ツインショック",
      "クレードルフレーム",
      "L型",
      "二気筒",
      "2バルブ",
      "フューエルインジェクション",
      "乾式クラッチ",
      "シャフトドライブ",
      "ABS",
      "セルスタート",
      "MT 6速",
      "アップライトポジション",
      "トラクションコントロール有",
      "ライディングモード有",
      "フルデジタル",
      "通勤・街乗り",
      "タンデム"
    ]
  },
  {
    "name": "V7 Stone Corsa",
    "maker": "Moto Guzzi",
    "model_code": null,
    "displacement": 853,
    "year": 2011,
    "max_power": 65.0,
    "max_torque": 73.0,
    "seat_height": 780,
    "wet_weight": 218,
    "fuel_economy": null,
    "status": "discontinued",
    "image_url": "https://image.bikebros.co.jp/bike_img/1/16559/1_s.jpg",
    "description": "Moto GuzziのBikeBrosカタログ掲載モデル。 2011年発売 853cc ネイキッド",
    "tags": [
      "Moto Guzzi",
      "ネイキッド",
      "空冷",
      "テレスコピックフォーク",
      "ツインショック",
      "クレードルフレーム",
      "L型",
      "二気筒",
      "2バルブ",
      "フューエルインジェクション",
      "乾式クラッチ",
      "シャフトドライブ",
      "ABS",
      "セルスタート",
      "MT 6速",
      "アップライトポジション",
      "トラクションコントロール有",
      "ライディングモード有",
      "フルデジタル",
      "通勤・街乗り",
      "タンデム"
    ]
  },
  {
    "name": "V85 STRADA",
    "maker": "Moto Guzzi",
    "model_code": null,
    "displacement": 853,
    "year": 2011,
    "max_power": null,
    "max_torque": 83.0,
    "seat_height": 830,
    "wet_weight": 226,
    "fuel_economy": null,
    "status": "discontinued",
    "image_url": "https://image.bikebros.co.jp/bike_img/1/17595/1_s.jpg",
    "description": "Moto GuzziのBikeBrosカタログ掲載モデル。 2011年発売 853cc ツアラー",
    "tags": [
      "Moto Guzzi",
      "ツアラー",
      "空冷",
      "倒立フォーク",
      "モノショック",
      "L型",
      "二気筒",
      "2バルブ",
      "フューエルインジェクション",
      "乾式クラッチ",
      "シャフトドライブ",
      "ABS",
      "セルスタート",
      "MT 6速",
      "アップライトポジション",
      "トラクションコントロール有",
      "ライディングモード有",
      "フルデジタル",
      "ツーリング",
      "タンデム"
    ]
  },
  {
    "name": "V85 TT",
    "maker": "Moto Guzzi",
    "model_code": null,
    "displacement": 853,
    "year": 2011,
    "max_power": null,
    "max_torque": 83.0,
    "seat_height": 830,
    "wet_weight": 230,
    "fuel_economy": null,
    "status": "discontinued",
    "image_url": "https://image.bikebros.co.jp/bike_img/1/17596/1_s.jpg",
    "description": "Moto GuzziのBikeBrosカタログ掲載モデル。 2011年発売 853cc ツアラー",
    "tags": [
      "Moto Guzzi",
      "ツアラー",
      "空冷",
      "倒立フォーク",
      "モノショック",
      "L型",
      "二気筒",
      "2バルブ",
      "フューエルインジェクション",
      "乾式クラッチ",
      "シャフトドライブ",
      "ABS",
      "セルスタート",
      "MT 6速",
      "アップライトポジション",
      "トラクションコントロール有",
      "ライディングモード有",
      "フルデジタル",
      "ツーリング",
      "タンデム"
    ]
  },
  {
    "name": "V85 TT Travel",
    "maker": "Moto Guzzi",
    "model_code": null,
    "displacement": 853,
    "year": 2011,
    "max_power": null,
    "max_torque": 83.0,
    "seat_height": 830,
    "wet_weight": 243,
    "fuel_economy": null,
    "status": "discontinued",
    "image_url": "https://image.bikebros.co.jp/bike_img/1/17597/1_s.jpg",
    "description": "Moto GuzziのBikeBrosカタログ掲載モデル。 2011年発売 853cc ツアラー",
    "tags": [
      "Moto Guzzi",
      "ツアラー",
      "空冷",
      "倒立フォーク",
      "モノショック",
      "L型",
      "二気筒",
      "2バルブ",
      "フューエルインジェクション",
      "乾式クラッチ",
      "シャフトドライブ",
      "ABS",
      "セルスタート",
      "MT 6速",
      "アップライトポジション",
      "トラクションコントロール有",
      "ライディングモード有",
      "フルデジタル",
      "ツーリング",
      "タンデム"
    ]
  },
  {
    "name": "V850 Le Mans",
    "maker": "Moto Guzzi",
    "model_code": null,
    "displacement": null,
    "year": 2011,
    "max_power": null,
    "max_torque": null,
    "seat_height": null,
    "wet_weight": null,
    "fuel_economy": null,
    "status": "discontinued",
    "image_url": "https://image.bikebros.co.jp/bike_img/no_photo_s.jpg",
    "description": "Moto GuzziのBikeBrosカタログ掲載モデル。 2011年発売 ツアラー",
    "tags": [
      "Moto Guzzi",
      "ツアラー",
      "アップライトポジション",
      "ツーリング"
    ]
  },
  {
    "name": "V850 Le Mans2",
    "maker": "Moto Guzzi",
    "model_code": null,
    "displacement": null,
    "year": 2011,
    "max_power": null,
    "max_torque": null,
    "seat_height": null,
    "wet_weight": null,
    "fuel_economy": null,
    "status": "discontinued",
    "image_url": "https://image.bikebros.co.jp/bike_img/no_photo_s.jpg",
    "description": "Moto GuzziのBikeBrosカタログ掲載モデル。 2011年発売 ツアラー",
    "tags": [
      "Moto Guzzi",
      "ツアラー",
      "アップライトポジション",
      "ツーリング"
    ]
  },
  {
    "name": "V850 Le Mans3",
    "maker": "Moto Guzzi",
    "model_code": null,
    "displacement": null,
    "year": 2011,
    "max_power": null,
    "max_torque": null,
    "seat_height": null,
    "wet_weight": null,
    "fuel_economy": null,
    "status": "discontinued",
    "image_url": "https://image.bikebros.co.jp/bike_img/no_photo_s.jpg",
    "description": "Moto GuzziのBikeBrosカタログ掲載モデル。 2011年発売 ツアラー",
    "tags": [
      "Moto Guzzi",
      "ツアラー",
      "アップライトポジション",
      "ツーリング"
    ]
  },
  {
    "name": "V9 ROAMER",
    "maker": "Moto Guzzi",
    "model_code": null,
    "displacement": 853,
    "year": 2011,
    "max_power": null,
    "max_torque": 82.0,
    "seat_height": 815,
    "wet_weight": null,
    "fuel_economy": null,
    "status": "discontinued",
    "image_url": "https://image.bikebros.co.jp/bike_img/1/15711/1_s.jpg",
    "description": "Moto GuzziのBikeBrosカタログ掲載モデル。 2011年発売 853cc ネイキッド",
    "tags": [
      "Moto Guzzi",
      "ネイキッド",
      "空冷",
      "テレスコピックフォーク",
      "ツインショック",
      "クレードルフレーム",
      "L型",
      "二気筒",
      "2バルブ",
      "フューエルインジェクション",
      "乾式クラッチ",
      "シャフトドライブ",
      "ABS",
      "セルスタート",
      "MT 6速",
      "アップライトポジション",
      "トラクションコントロール有",
      "アナログ",
      "通勤・街乗り",
      "タンデム"
    ]
  },
  {
    "name": "その他のモデル",
    "maker": "Moto Guzzi",
    "model_code": null,
    "displacement": null,
    "year": 2011,
    "max_power": null,
    "max_torque": null,
    "seat_height": null,
    "wet_weight": null,
    "fuel_economy": null,
    "status": "discontinued",
    "image_url": "https://image.bikebros.co.jp/bike_img/no_photo_s.jpg",
    "description": "Moto GuzziのBikeBrosカタログ掲載モデル。 2011年発売",
    "tags": [
      "Moto Guzzi"
    ]
  },
  {
    "name": "V7 Classic",
    "maker": "Moto Guzzi",
    "model_code": null,
    "displacement": 744,
    "year": 2012,
    "max_power": 40.1,
    "max_torque": 50.0,
    "seat_height": 805,
    "wet_weight": null,
    "fuel_economy": null,
    "status": "discontinued",
    "image_url": "https://image.bikebros.co.jp/bike_img/0/5765/1_s.jpg",
    "description": "Moto GuzziのBikeBrosカタログ掲載モデル。 2012年発売 744cc ネイキッド",
    "tags": [
      "Moto Guzzi",
      "ネイキッド",
      "空冷",
      "テレスコピックフォーク",
      "モノショック",
      "L型",
      "二気筒",
      "2バルブ",
      "フューエルインジェクション",
      "乾式クラッチ",
      "シャフトドライブ",
      "セルスタート",
      "MT 5速",
      "アップライトポジション",
      "通勤・街乗り"
    ]
  },
  {
    "name": "1200 Sport 4V ABS",
    "maker": "Moto Guzzi",
    "model_code": null,
    "displacement": 1151,
    "year": 2013,
    "max_power": 87.0,
    "max_torque": 111.0,
    "seat_height": 800,
    "wet_weight": 245,
    "fuel_economy": null,
    "status": "discontinued",
    "image_url": "https://image.bikebros.co.jp/bike_img/0/5710/1_s.jpg",
    "description": "Moto GuzziのBikeBrosカタログ掲載モデル。 2013年発売 1151cc ネイキッド",
    "tags": [
      "Moto Guzzi",
      "ネイキッド",
      "空冷",
      "テレスコピックフォーク",
      "モノショック",
      "L型",
      "二気筒",
      "4バルブ",
      "フューエルインジェクション",
      "乾式クラッチ",
      "シャフトドライブ",
      "セルスタート",
      "MT 6速",
      "アップライトポジション",
      "通勤・街乗り"
    ]
  },
  {
    "name": "California 1400 Custom",
    "maker": "Moto Guzzi",
    "model_code": null,
    "displacement": 1380,
    "year": 2013,
    "max_power": null,
    "max_torque": 120.0,
    "seat_height": 740,
    "wet_weight": 318,
    "fuel_economy": null,
    "status": "discontinued",
    "image_url": "https://image.bikebros.co.jp/bike_img/0/5714/1_s.jpg",
    "description": "Moto GuzziのBikeBrosカタログ掲載モデル。 2013年発売 1380cc ツアラー",
    "tags": [
      "Moto Guzzi",
      "ツアラー",
      "空冷",
      "テレスコピックフォーク",
      "モノショック",
      "L型",
      "二気筒",
      "4バルブ",
      "フューエルインジェクション",
      "乾式クラッチ",
      "セルスタート",
      "MT 6速",
      "アップライトポジション",
      "ツーリング"
    ]
  },
  {
    "name": "V7 Racer",
    "maker": "Moto Guzzi",
    "model_code": null,
    "displacement": 744,
    "year": 2015,
    "max_power": null,
    "max_torque": 60.0,
    "seat_height": 805,
    "wet_weight": null,
    "fuel_economy": null,
    "status": "discontinued",
    "image_url": "https://image.bikebros.co.jp/bike_img/0/5771/1_s.jpg",
    "description": "Moto GuzziのBikeBrosカタログ掲載モデル。 2015年発売 744cc ネイキッド",
    "tags": [
      "Moto Guzzi",
      "ネイキッド",
      "空冷",
      "テレスコピックフォーク",
      "モノショック",
      "L型",
      "二気筒",
      "2バルブ",
      "フューエルインジェクション",
      "乾式クラッチ",
      "シャフトドライブ",
      "セルスタート",
      "MT 5速",
      "アップライトポジション",
      "通勤・街乗り"
    ]
  },
  {
    "name": "V7 ⅡStone",
    "maker": "Moto Guzzi",
    "model_code": null,
    "displacement": 744,
    "year": 2015,
    "max_power": null,
    "max_torque": 60.0,
    "seat_height": 790,
    "wet_weight": 189,
    "fuel_economy": null,
    "status": "discontinued",
    "image_url": "https://image.bikebros.co.jp/bike_img/0/5758/1_s.jpg",
    "description": "Moto GuzziのBikeBrosカタログ掲載モデル。 2015年発売 744cc ネイキッド",
    "tags": [
      "Moto Guzzi",
      "ネイキッド",
      "空冷",
      "テレスコピックフォーク",
      "モノショック",
      "L型",
      "二気筒",
      "2バルブ",
      "フューエルインジェクション",
      "乾式クラッチ",
      "シャフトドライブ",
      "セルスタート",
      "MT 6速",
      "アップライトポジション",
      "通勤・街乗り"
    ]
  },
  {
    "name": "V7 Ⅱ Racer",
    "maker": "Moto Guzzi",
    "model_code": null,
    "displacement": 744,
    "year": 2016,
    "max_power": null,
    "max_torque": 60.0,
    "seat_height": 790,
    "wet_weight": 190,
    "fuel_economy": null,
    "status": "discontinued",
    "image_url": "https://image.bikebros.co.jp/bike_img/0/5757/1_s.jpg",
    "description": "Moto GuzziのBikeBrosカタログ掲載モデル。 2016年発売 744cc ネイキッド",
    "tags": [
      "Moto Guzzi",
      "ネイキッド",
      "空冷",
      "テレスコピックフォーク",
      "モノショック",
      "L型",
      "二気筒",
      "2バルブ",
      "フューエルインジェクション",
      "乾式クラッチ",
      "シャフトドライブ",
      "セルスタート",
      "MT 6速",
      "アップライトポジション",
      "通勤・街乗り"
    ]
  },
  {
    "name": "V7-2 Stornello",
    "maker": "Moto Guzzi",
    "model_code": null,
    "displacement": 744,
    "year": 2016,
    "max_power": null,
    "max_torque": 60.0,
    "seat_height": 798,
    "wet_weight": null,
    "fuel_economy": null,
    "status": "discontinued",
    "image_url": "https://image.bikebros.co.jp/bike_img/0/5782/1_s.jpg",
    "description": "Moto GuzziのBikeBrosカタログ掲載モデル。 2016年発売 744cc ネイキッド",
    "tags": [
      "Moto Guzzi",
      "ネイキッド",
      "空冷",
      "テレスコピックフォーク",
      "ツインショック",
      "クレードルフレーム",
      "L型",
      "二気筒",
      "2バルブ",
      "フューエルインジェクション",
      "乾式クラッチ",
      "シャフトドライブ",
      "セルスタート",
      "MT 6速",
      "アップライトポジション",
      "通勤・街乗り",
      "タンデム"
    ]
  },
  {
    "name": "V7 Ⅲ Anniversario",
    "maker": "Moto Guzzi",
    "model_code": null,
    "displacement": 744,
    "year": 2017,
    "max_power": null,
    "max_torque": 60.0,
    "seat_height": 770,
    "wet_weight": 213,
    "fuel_economy": null,
    "status": "discontinued",
    "image_url": "https://image.bikebros.co.jp/bike_img/0/5759/1_s.jpg",
    "description": "Moto GuzziのBikeBrosカタログ掲載モデル。 2017年発売 744cc ネイキッド",
    "tags": [
      "Moto Guzzi",
      "ネイキッド",
      "空冷",
      "テレスコピックフォーク",
      "ツインショック",
      "クレードルフレーム",
      "L型",
      "二気筒",
      "2バルブ",
      "フューエルインジェクション",
      "乾式クラッチ",
      "シャフトドライブ",
      "ABS",
      "セルスタート",
      "MT 6速",
      "アップライトポジション",
      "トラクションコントロール有",
      "アナログ",
      "通勤・街乗り",
      "タンデム"
    ]
  },
  {
    "name": "V7 Ⅲ Carbon",
    "maker": "Moto Guzzi",
    "model_code": null,
    "displacement": 744,
    "year": 2018,
    "max_power": null,
    "max_torque": 60.0,
    "seat_height": 770,
    "wet_weight": 209,
    "fuel_economy": null,
    "status": "discontinued",
    "image_url": "https://image.bikebros.co.jp/bike_img/1/13252/1_s.jpg",
    "description": "Moto GuzziのBikeBrosカタログ掲載モデル。 2018年発売 744cc ネイキッド",
    "tags": [
      "Moto Guzzi",
      "ネイキッド",
      "空冷",
      "テレスコピックフォーク",
      "ツインショック",
      "クレードルフレーム",
      "L型",
      "二気筒",
      "2バルブ",
      "フューエルインジェクション",
      "乾式クラッチ",
      "シャフトドライブ",
      "ABS",
      "セルスタート",
      "MT 6速",
      "アップライトポジション",
      "トラクションコントロール有",
      "アナログ",
      "通勤・街乗り",
      "タンデム"
    ]
  },
  {
    "name": "V7 Ⅲ CarbonShine",
    "maker": "Moto Guzzi",
    "model_code": null,
    "displacement": 744,
    "year": 2018,
    "max_power": null,
    "max_torque": 60.0,
    "seat_height": 770,
    "wet_weight": 209,
    "fuel_economy": null,
    "status": "discontinued",
    "image_url": "https://image.bikebros.co.jp/bike_img/1/13466/1_s.jpg",
    "description": "Moto GuzziのBikeBrosカタログ掲載モデル。 2018年発売 744cc ネイキッド",
    "tags": [
      "Moto Guzzi",
      "ネイキッド",
      "空冷",
      "テレスコピックフォーク",
      "ツインショック",
      "クレードルフレーム",
      "L型",
      "二気筒",
      "2バルブ",
      "フューエルインジェクション",
      "乾式クラッチ",
      "シャフトドライブ",
      "ABS",
      "セルスタート",
      "MT 6速",
      "アップライトポジション",
      "トラクションコントロール有",
      "アナログ",
      "通勤・街乗り",
      "タンデム"
    ]
  },
  {
    "name": "V7 Ⅲ Milano",
    "maker": "Moto Guzzi",
    "model_code": null,
    "displacement": 744,
    "year": 2018,
    "max_power": null,
    "max_torque": 60.0,
    "seat_height": 770,
    "wet_weight": 209,
    "fuel_economy": null,
    "status": "discontinued",
    "image_url": "https://image.bikebros.co.jp/bike_img/1/13251/1_s.jpg",
    "description": "Moto GuzziのBikeBrosカタログ掲載モデル。 2018年発売 744cc ネイキッド",
    "tags": [
      "Moto Guzzi",
      "ネイキッド",
      "空冷",
      "テレスコピックフォーク",
      "ツインショック",
      "クレードルフレーム",
      "L型",
      "二気筒",
      "2バルブ",
      "フューエルインジェクション",
      "乾式クラッチ",
      "シャフトドライブ",
      "ABS",
      "セルスタート",
      "MT 6速",
      "アップライトポジション",
      "トラクションコントロール有",
      "アナログ",
      "通勤・街乗り",
      "タンデム"
    ]
  },
  {
    "name": "V7 Ⅲ ROUGH",
    "maker": "Moto Guzzi",
    "model_code": null,
    "displacement": 744,
    "year": 2019,
    "max_power": null,
    "max_torque": 60.0,
    "seat_height": 770,
    "wet_weight": 209,
    "fuel_economy": null,
    "status": "discontinued",
    "image_url": "https://image.bikebros.co.jp/bike_img/1/14071/1_s.jpg",
    "description": "Moto GuzziのBikeBrosカタログ掲載モデル。 2019年発売 744cc ネイキッド",
    "tags": [
      "Moto Guzzi",
      "ネイキッド",
      "空冷",
      "テレスコピックフォーク",
      "ツインショック",
      "クレードルフレーム",
      "L型",
      "二気筒",
      "2バルブ",
      "フューエルインジェクション",
      "乾式クラッチ",
      "シャフトドライブ",
      "ABS",
      "セルスタート",
      "MT 6速",
      "アップライトポジション",
      "トラクションコントロール有",
      "通勤・街乗り",
      "タンデム"
    ]
  },
  {
    "name": "V7 Ⅲ Stone",
    "maker": "Moto Guzzi",
    "model_code": null,
    "displacement": 744,
    "year": 2019,
    "max_power": null,
    "max_torque": 60.0,
    "seat_height": 770,
    "wet_weight": 209,
    "fuel_economy": null,
    "status": "discontinued",
    "image_url": "https://image.bikebros.co.jp/bike_img/1/13731/1_s.jpg",
    "description": "Moto GuzziのBikeBrosカタログ掲載モデル。 2019年発売 744cc ネイキッド",
    "tags": [
      "Moto Guzzi",
      "ネイキッド",
      "空冷",
      "テレスコピックフォーク",
      "ツインショック",
      "クレードルフレーム",
      "L型",
      "二気筒",
      "2バルブ",
      "フューエルインジェクション",
      "乾式クラッチ",
      "シャフトドライブ",
      "ABS",
      "セルスタート",
      "MT 6速",
      "アップライトポジション",
      "トラクションコントロール有",
      "通勤・街乗り",
      "タンデム"
    ]
  },
  {
    "name": "V7 Ⅲ Stone NIGHT PACK",
    "maker": "Moto Guzzi",
    "model_code": null,
    "displacement": 744,
    "year": 2019,
    "max_power": null,
    "max_torque": 60.0,
    "seat_height": 770,
    "wet_weight": 209,
    "fuel_economy": null,
    "status": "discontinued",
    "image_url": "https://image.bikebros.co.jp/bike_img/1/14072/1_s.jpg",
    "description": "Moto GuzziのBikeBrosカタログ掲載モデル。 2019年発売 744cc ネイキッド",
    "tags": [
      "Moto Guzzi",
      "ネイキッド",
      "空冷",
      "テレスコピックフォーク",
      "ツインショック",
      "クレードルフレーム",
      "L型",
      "二気筒",
      "2バルブ",
      "フューエルインジェクション",
      "乾式クラッチ",
      "シャフトドライブ",
      "ABS",
      "セルスタート",
      "MT 6速",
      "アップライトポジション",
      "トラクションコントロール有",
      "アナログ",
      "通勤・街乗り",
      "タンデム"
    ]
  },
  {
    "name": "V9 BOBBER SPORT",
    "maker": "Moto Guzzi",
    "model_code": null,
    "displacement": 853,
    "year": 2019,
    "max_power": null,
    "max_torque": 62.0,
    "seat_height": 785,
    "wet_weight": 210,
    "fuel_economy": null,
    "status": "discontinued",
    "image_url": "https://image.bikebros.co.jp/bike_img/1/13317/1_s.jpg",
    "description": "Moto GuzziのBikeBrosカタログ掲載モデル。 2019年発売 853cc ネイキッド",
    "tags": [
      "Moto Guzzi",
      "ネイキッド",
      "油冷",
      "テレスコピックフォーク",
      "ツインショック",
      "クレードルフレーム",
      "L型",
      "二気筒",
      "2バルブ",
      "フューエルインジェクション",
      "乾式クラッチ",
      "シャフトドライブ",
      "ABS",
      "セルスタート",
      "MT 6速",
      "アップライトポジション",
      "トラクションコントロール有",
      "通勤・街乗り"
    ]
  },
  {
    "name": "V7 Ⅲ Racer 10th ANNIVERSARY",
    "maker": "Moto Guzzi",
    "model_code": null,
    "displacement": 744,
    "year": 2020,
    "max_power": null,
    "max_torque": 60.0,
    "seat_height": 770,
    "wet_weight": 209,
    "fuel_economy": null,
    "status": "discontinued",
    "image_url": "https://image.bikebros.co.jp/bike_img/1/14584/1_s.jpg",
    "description": "Moto GuzziのBikeBrosカタログ掲載モデル。 2020年発売 744cc ネイキッド",
    "tags": [
      "Moto Guzzi",
      "ネイキッド",
      "空冷",
      "テレスコピックフォーク",
      "ツインショック",
      "クレードルフレーム",
      "L型",
      "二気筒",
      "2バルブ",
      "フューエルインジェクション",
      "乾式クラッチ",
      "シャフトドライブ",
      "ABS",
      "セルスタート",
      "MT 6速",
      "アップライトポジション",
      "トラクションコントロール有",
      "アナログ",
      "通勤・街乗り",
      "タンデム"
    ]
  },
  {
    "name": "V7 Ⅲ Special",
    "maker": "Moto Guzzi",
    "model_code": null,
    "displacement": 744,
    "year": 2020,
    "max_power": null,
    "max_torque": 60.0,
    "seat_height": 770,
    "wet_weight": 213,
    "fuel_economy": null,
    "status": "discontinued",
    "image_url": "https://image.bikebros.co.jp/bike_img/1/15004/1_s.jpg",
    "description": "Moto GuzziのBikeBrosカタログ掲載モデル。 2020年発売 744cc ネイキッド",
    "tags": [
      "Moto Guzzi",
      "ネイキッド",
      "空冷",
      "テレスコピックフォーク",
      "ツインショック",
      "クレードルフレーム",
      "L型",
      "二気筒",
      "2バルブ",
      "フューエルインジェクション",
      "乾式クラッチ",
      "ABS",
      "セルスタート",
      "MT 6速",
      "アップライトポジション",
      "トラクションコントロール有",
      "アナログ",
      "通勤・街乗り",
      "タンデム"
    ]
  },
  {
    "name": "V7 Ⅲ Stone S",
    "maker": "Moto Guzzi",
    "model_code": null,
    "displacement": 744,
    "year": 2020,
    "max_power": null,
    "max_torque": 60.0,
    "seat_height": 770,
    "wet_weight": 209,
    "fuel_economy": null,
    "status": "discontinued",
    "image_url": "https://image.bikebros.co.jp/bike_img/1/14583/1_s.jpg",
    "description": "Moto GuzziのBikeBrosカタログ掲載モデル。 2020年発売 744cc ネイキッド",
    "tags": [
      "Moto Guzzi",
      "ネイキッド",
      "空冷",
      "テレスコピックフォーク",
      "ツインショック",
      "クレードルフレーム",
      "L型",
      "二気筒",
      "2バルブ",
      "フューエルインジェクション",
      "乾式クラッチ",
      "シャフトドライブ",
      "ABS",
      "セルスタート",
      "MT 6速",
      "アップライトポジション",
      "トラクションコントロール有",
      "アナログ",
      "通勤・街乗り",
      "タンデム"
    ]
  },
  {
    "name": "V9 BOBBER SPECIAL EDITION",
    "maker": "Moto Guzzi",
    "model_code": null,
    "displacement": 853,
    "year": 2023,
    "max_power": null,
    "max_torque": 73.0,
    "seat_height": 785,
    "wet_weight": 210,
    "fuel_economy": null,
    "status": "discontinued",
    "image_url": "https://image.bikebros.co.jp/bike_img/1/16391/1_s.jpg",
    "description": "Moto GuzziのBikeBrosカタログ掲載モデル。 2023年発売 853cc ネイキッド",
    "tags": [
      "Moto Guzzi",
      "ネイキッド",
      "空冷",
      "テレスコピックフォーク",
      "ツインショック",
      "クレードルフレーム",
      "L型",
      "二気筒",
      "2バルブ",
      "フューエルインジェクション",
      "乾式クラッチ",
      "シャフトドライブ",
      "ABS",
      "セルスタート",
      "MT 6速",
      "アップライトポジション",
      "トラクションコントロール有",
      "フルデジタル",
      "通勤・街乗り",
      "タンデム"
    ]
  },
  {
    "name": "V7 Stone TEN",
    "maker": "Moto Guzzi",
    "model_code": null,
    "displacement": 853,
    "year": 2024,
    "max_power": null,
    "max_torque": 75.0,
    "seat_height": 780,
    "wet_weight": 218,
    "fuel_economy": null,
    "status": "current",
    "image_url": "https://image.bikebros.co.jp/bike_img/1/16714/1_s.jpg",
    "description": "Moto GuzziのBikeBrosカタログ掲載モデル。 2024年発売 853cc ネイキッド",
    "tags": [
      "Moto Guzzi",
      "ネイキッド",
      "空冷",
      "テレスコピックフォーク",
      "ツインショック",
      "クレードルフレーム",
      "L型",
      "二気筒",
      "2バルブ",
      "フューエルインジェクション",
      "乾式クラッチ",
      "ABS",
      "セルスタート",
      "MT 6速",
      "アップライトポジション",
      "トラクションコントロール有",
      "ライディングモード有",
      "フルデジタル",
      "通勤・街乗り",
      "タンデム"
    ]
  },
  {
    "name": "V7 Special",
    "maker": "Moto Guzzi",
    "model_code": null,
    "displacement": 853,
    "year": 2025,
    "max_power": null,
    "max_torque": 79.0,
    "seat_height": 780,
    "wet_weight": 223,
    "fuel_economy": null,
    "status": "current",
    "image_url": "https://image.bikebros.co.jp/bike_img/1/17051/1_s.jpg",
    "description": "Moto GuzziのBikeBrosカタログ掲載モデル。 2025年発売 853cc ネイキッド",
    "tags": [
      "Moto Guzzi",
      "ネイキッド",
      "空冷",
      "テレスコピックフォーク",
      "ツインショック",
      "クレードルフレーム",
      "L型",
      "二気筒",
      "2バルブ",
      "フューエルインジェクション",
      "乾式クラッチ",
      "シャフトドライブ",
      "ABS",
      "セルスタート",
      "MT 6速",
      "アップライトポジション",
      "トラクションコントロール有",
      "ライディングモード有",
      "フルデジタル",
      "通勤・街乗り",
      "タンデム"
    ]
  }
]